mkdocs_pseudocode_plugin/__init__.py
mkdocs_pseudocode_plugin/plugin.py
mkdocs_pseudocode-0.1.4.dist-info/LICENCE
mkdocs_pseudocode-0.1.4.dist-info/METADATA
mkdocs_pseudocode-0.1.4.dist-info/WHEEL
mkdocs_pseudocode-0.1.4.dist-info/entry_points.txt
mkdocs_pseudocode-0.1.4.dist-info/top_level.txt
mkdocs_pseudocode-0.1.4.dist-info/RECORD
