Metadata-Version: 2.1
Name: mkdocs-pseudocode
Version: 0.1.4
Summary: A MkDocs plugin to render beautiful pseudocode with LaTeX-inspired syntax.
Home-page: https://github.com/JulesTopart/mkdocs-pseudocode
Author: Jules Topart
Author-email: jules.topart@gmail.com
License: MIT
Classifier: Development Status :: 3 - Alpha
Classifier: Intended Audience :: Developers
Classifier: License :: OSI Approved :: MIT License
Classifier: Programming Language :: Python :: 3
Classifier: Programming Language :: Python :: 3.7
Classifier: Programming Language :: Python :: 3.8
Classifier: Programming Language :: Python :: 3.9
Classifier: Programming Language :: Python :: 3.10
Classifier: Topic :: Documentation
Classifier: Topic :: Software Development :: Documentation
License-File: LICENCE
Requires-Dist: mkdocs
Requires-Dist: mkdocs-material
